mpdaf-3.6.data/scripts/topcat_show_ds9
mpdaf-3.6.dist-info/RECORD
mpdaf-3.6.dist-info/LICENSE
mpdaf-3.6.dist-info/WHEEL
mpdaf-3.6.dist-info/entry_points.txt
mpdaf-3.6.dist-info/top_level.txt
mpdaf-3.6.dist-info/METADATA
mpdaf/conftest.py
mpdaf/version.py
mpdaf/log.py
mpdaf/__init__.py
mpdaf/obj/objs.py
mpdaf/obj/arithmetic.py
mpdaf/obj/plot.py
mpdaf/obj/coords.py
mpdaf/obj/wavelet1D.py
mpdaf/obj/__init__.py
mpdaf/obj/masking.py
mpdaf/obj/merging.c
mpdaf/obj/merging.pyx
mpdaf/obj/merging.cpython-311-darwin.so
mpdaf/obj/ABmag_filters.py
mpdaf/obj/spectrum.py
mpdaf/obj/cube.py
mpdaf/obj/fitting.py
mpdaf/obj/image.py
mpdaf/obj/cubelist.py
mpdaf/obj/data.py
mpdaf/obj/filters/filter_list.fits
mpdaf/obj/tests/test_objs.py
mpdaf/obj/tests/test_image.py
mpdaf/obj/tests/__init__.py
mpdaf/obj/tests/test_cube.py
mpdaf/obj/tests/test_cubelist.py
mpdaf/obj/tests/test_coords.py
mpdaf/obj/tests/test_data.py
mpdaf/obj/tests/test_wavelet1D.py
mpdaf/obj/tests/test_spectrum.py
mpdaf/tools/fits.py
mpdaf/tools/util.py
mpdaf/tools/__init__.py
mpdaf/tools/euro3D.py
mpdaf/tools/ctools.py
mpdaf/tools/tests/test_fits.py
mpdaf/tools/tests/__init__.py
mpdaf/MUSE/__init__.py
mpdaf/MUSE/PSF.py
mpdaf/MUSE/fsf.py
mpdaf/MUSE/slicer.py
mpdaf/MUSE/FieldsMap.py
mpdaf/MUSE/tests/test_PSF.py
mpdaf/MUSE/tests/__init__.py
mpdaf/MUSE/tests/test_fsf.py
mpdaf/sdetect/catalog.py
mpdaf/sdetect/linelist.py
mpdaf/sdetect/sea.py
mpdaf/sdetect/__init__.py
mpdaf/sdetect/muselet.py
mpdaf/sdetect/segmap.py
mpdaf/sdetect/source.py
mpdaf/sdetect/sea_data/gauss_3.0_5x5.conv
mpdaf/sdetect/sea_data/gauss_5.0_9x9.conv
mpdaf/sdetect/sea_data/default.nnw
mpdaf/sdetect/sea_data/default.sex
mpdaf/sdetect/sea_data/default.param
mpdaf/sdetect/tests/test_catalog.py
mpdaf/sdetect/tests/test_segmap.py
mpdaf/sdetect/tests/test_linelist.py
mpdaf/sdetect/tests/test_source.py
mpdaf/sdetect/tests/__init__.py
mpdaf/sdetect/tests/test_muselet.py
mpdaf/sdetect/tests/test_sourcelist.py
mpdaf/sdetect/muselet_data/emlines_small
mpdaf/sdetect/muselet_data/default.conv
mpdaf/sdetect/muselet_data/emlines
mpdaf/sdetect/muselet_data/nb_default.conv
