Metadata-Version: 2.1
Name: mpdaf
Version: 3.6
Summary: MUSE Python Data Analysis Framework is a python framework in view of the analysis of MUSE data in the context of the GTO.
Home-page: https://git-cral.univ-lyon1.fr/MUSE/mpdaf
Maintainer: Laure Piqueras
Maintainer-email: laure.piqueras@univ-lyon1.fr
License: BSD
Keywords: astronomy,astrophysics,science,muse,vlt,cube,image,spectrum
Platform: any
Classifier: Development Status :: 5 - Production/Stable
Classifier: Intended Audience :: Science/Research
Classifier: License :: OSI Approved :: BSD License
Classifier: Operating System :: OS Independent
Classifier: Programming Language :: C
Classifier: Programming Language :: Cython
Classifier: Programming Language :: Python :: 3
Classifier: Programming Language :: Python :: Implementation :: CPython
Classifier: Topic :: Scientific/Engineering :: Astronomy
Classifier: Topic :: Scientific/Engineering :: Physics
Requires-Python: >=3.9
License-File: LICENSE
Requires-Dist: numpy>=1.10.0
Requires-Dist: scipy>=1.11.0
Requires-Dist: matplotlib
Requires-Dist: astropy>=1.0
Requires-Dist: specutils
Provides-Extra: all
Requires-Dist: numexpr; extra == "all"
Requires-Dist: fitsio; extra == "all"
Requires-Dist: adjustText; extra == "all"
Requires-Dist: joblib; extra == "all"
Requires-Dist: tqdm; extra == "all"
Requires-Dist: specutils; extra == "all"
Provides-Extra: docs
Requires-Dist: sphinx; extra == "docs"
Requires-Dist: sphinx_rtd_theme; extra == "docs"
Requires-Dist: sphinx_automodapi; extra == "docs"
Requires-Dist: numpydoc; extra == "docs"
Requires-Dist: ipython; extra == "docs"
Requires-Dist: psutil; extra == "docs"
Requires-Dist: specutils; extra == "docs"
